crous/__init__.py
crous/__init__.pyi
crous/crous.cpython-314-darwin.so
crous/pycrous.c
crous/version.py
crous/include/crous.h
crous/include/crous_arena.h
crous/include/crous_binary.h
crous/include/crous_errors.h
crous/include/crous_flux.h
crous/include/crous_lexer.h
crous/include/crous_parser.h
crous/include/crous_token.h
crous/include/crous_types.h
crous/include/crous_value.h
crous/include/crous_version.h
crous/src/c/binary/binary.c
crous/src/c/core/arena.c
crous/src/c/core/errors.c
crous/src/c/core/value.c
crous/src/c/core/version.c
crous/src/c/flux/flux_lexer.c
crous/src/c/flux/flux_parser.c
crous/src/c/flux/flux_serializer.c
crous/src/c/lexer/lexer.c
crous/src/c/parser/parser.c
crous/src/c/utils/token.c
crous-1.0.3.dist-info/licenses/LICENSE
crous-1.0.3.dist-info/METADATA
crous-1.0.3.dist-info/WHEEL
crous-1.0.3.dist-info/top_level.txt
crous-1.0.3.dist-info/RECORD
